spafw37/__init__.py
spafw37/cli.py
spafw37/command.py
spafw37/config.py
spafw37/config_func.py
spafw37/configure.py
spafw37/core.py
spafw37/cycle.py
spafw37/help.py
spafw37/logging.py
spafw37/logging_config.py
spafw37/param.py
spafw37/constants/__init__.py
spafw37/constants/command.py
spafw37/constants/config.py
spafw37/constants/cycle.py
spafw37/constants/logging.py
spafw37/constants/param.py
spafw37/constants/phase.py
spafw37-1.0.1.dist-info/LICENSE.md
spafw37-1.0.1.dist-info/METADATA
spafw37-1.0.1.dist-info/WHEEL
spafw37-1.0.1.dist-info/top_level.txt
spafw37-1.0.1.dist-info/RECORD
