Metadata-Version: 2.1
Name: spafw37
Version: 1.0.1
Summary: Simple framework for command line driven applications in Python 3.7
Home-page: https://github.com/minouris/spafw37
Author: Ciara Norrish
Author-email: minouris@users.noreply.github.com
License: MIT
Requires-Python: <4,>=3.7
License-File: LICENSE.md
Provides-Extra: dev
Requires-Dist: pytest ==6.2.5 ; extra == 'dev'
Requires-Dist: pytest-cov ==2.12.1 ; extra == 'dev'
